ennemi/__init__.py
ennemi/_driver.py
ennemi/_entropy_estimators.py
ennemi/py.typed
ennemi-1.5.0.dist-info/LICENSE.md
ennemi-1.5.0.dist-info/METADATA
ennemi-1.5.0.dist-info/WHEEL
ennemi-1.5.0.dist-info/top_level.txt
ennemi-1.5.0.dist-info/RECORD
