Metadata-Version: 2.1
Name: ennemi
Version: 1.5.0
Summary: Non-linear correlation detection with mutual information
Home-page: https://polsys.github.io/ennemi/
Author: Petri Laarne
Author-email: petri.laarne@helsinki.fi
License: MIT
Project-URL: Documentation, https://polsys.github.io/ennemi/
Project-URL: Source, https://github.com/polsys/ennemi/
Project-URL: Issues, https://github.com/polsys/ennemi/issues
Project-URL: Zenodo, https://doi.org/10.5281/zenodo.3834018
Keywords: information-theory entropy mutual-information data-analysis scientific
Classifier: Development Status :: 5 - Production/Stable
Classifier: Intended Audience :: Science/Research
Classifier: License :: OSI Approved :: MIT License
Classifier: Operating System :: OS Independent
Classifier: Programming Language :: Python :: 3
Classifier: Programming Language :: Python :: 3.11
Classifier: Programming Language :: Python :: 3.12
Classifier: Programming Language :: Python :: 3.13
Classifier: Topic :: Scientific/Engineering
Classifier: Topic :: Scientific/Engineering :: Information Analysis
Classifier: Topic :: Scientific/Engineering :: Mathematics
Classifier: Topic :: Scientific/Engineering :: Physics
Classifier: Typing :: Typed
Requires-Python: ~=3.11
License-File: LICENSE.md
Requires-Dist: numpy>=1.24
Requires-Dist: scipy~=1.10
Provides-Extra: dev
Requires-Dist: build~=1.2; extra == "dev"
Requires-Dist: pandas>=2.0; extra == "dev"
Requires-Dist: pytest~=8.0; extra == "dev"
Requires-Dist: mypy~=1.9; extra == "dev"
